dem_decoders/__init__.py
dem_decoders/bplsd.py
dem_decoders/bposd.py
dem_decoders/bpuf.py
dem_decoders/scanners.py
dem_decoders/transformations.py
dem_decoders/util.py
dem_decoders-0.1.1.dist-info/licenses/LICENSE
dem_decoders-0.1.1.dist-info/METADATA
dem_decoders-0.1.1.dist-info/WHEEL
dem_decoders-0.1.1.dist-info/top_level.txt
dem_decoders-0.1.1.dist-info/RECORD
