Metadata-Version: 2.4
Name: dem-decoders
Version: 0.1.1
Summary: Wrapped decoders to work with stim.DetectorErrorModel
Author-email: Marc Serra Peralta <marcserraperalta@gmail.com>
Maintainer-email: Marc Serra Peralta <marcserraperalta@gmail.com>
License: MIT License
Keywords: stim,DetectorErrorModel,QEC
Requires-Python: >=3.10
License-File: LICENSE
Requires-Dist: numpy
Requires-Dist: stim
Requires-Dist: scipy
Requires-Dist: ldpc
Requires-Dist: sinter>=1.15.0
Requires-Dist: tqdm
Provides-Extra: dev
Requires-Dist: pip-tools; extra == "dev"
Requires-Dist: pytest; extra == "dev"
Requires-Dist: scalene; extra == "dev"
Requires-Dist: black; extra == "dev"
Requires-Dist: pytest-black; extra == "dev"
Dynamic: license-file
